{
  "version": 2,
  "type": "poster-v2",
  "uid": "6c476ccd-940d-4083-9544-3ff483187f98",
  "front": {
    "title": "AI Ethics in China",
    "subtitle": "Draft placeholder - Wikipedia lookup requires review"
  },
  "back": {
    "layout": "text-only",
    "text": "Automatic Wikipedia generation did not return a definitive article for this topic.\n\nOriginal topic: AI_Ethics_in_China\nReason: 404 Client Error: Not Found for url: https://en.wikipedia.org/api/rest_v1/page/summary/AI_Ethics_in_China\n\nNext step: edit this poster in Unified Editor with the intended subject details.\n\nPossible clarifications:\n- Regulation_of_artificial_intelligence\n- Ethics_of_artificial_intelligence\n- Artificial_intelligence_controversies\n- History_of_artificial_intelligence\n- Artificial_intelligence_industry_in_China",
    "links": []
  },
  "meta": {
    "created": "2026-03-18T23:27:42.978296",
    "modified": "2026-03-18T23:27:42.978302",
    "categories": [
      "Chinese Open Weight Models"
    ],
    "tags": [
      "AI Ethics in China"
    ],
    "source": "",
    "needs_review": true
  }
}